mnist_fpga/hdl/sim/tb_start_reset.v
// Simple testbench to verify start/reset button functionality
`timescale 1ns/1ps

module tb_start_reset;

  reg clk;
  reg rst_n;
  reg start_btn;
  wire done;
  wire [3:0] predicted_digit;

  // Clock generation
  initial begin
    clk = 0;
    forever #5 clk = ~clk; // 100MHz clock
  end

  // Simple top module for testing (without neural network layers)
  reg [2:0] tstate;
  reg start_btn_sync1, start_btn_sync2, start_btn_prev;
  wire start_btn_edge = start_btn_sync2 & ~start_btn_prev;
  wire rst = ~rst_n;
  
  reg done_reg;
  reg [3:0] predicted_digit_reg;
  
  assign done = done_reg;
  assign predicted_digit = predicted_digit_reg;

  localparam T_IDLE   = 3'd0;
  localparam T_WAIT   = 3'd1;
  localparam T_CALC   = 3'd2;
  localparam T_DONE   = 3'd3;

  // Button synchronization
  always @(posedge clk) begin
    if (rst) begin
      start_btn_sync1 <= 1'b0;
      start_btn_sync2 <= 1'b0;
      start_btn_prev <= 1'b0;
    end else begin
      start_btn_sync1 <= start_btn;
      start_btn_sync2 <= start_btn_sync1;
      start_btn_prev <= start_btn_sync2;
    end
  end

  // Simple FSM to test start/reset functionality
  reg [7:0] calc_counter;
  
  always @(posedge clk) begin
    if (rst) begin
      tstate <= T_IDLE;
      done_reg <= 1'b0;
      predicted_digit_reg <= 4'd0;
      calc_counter <= 8'd0;
    end else begin
      case (tstate)
        T_IDLE: begin
          done_reg <= 1'b0;
          predicted_digit_reg <= 4'd0;
          tstate <= T_WAIT;
        end

        T_WAIT: begin
          done_reg <= 1'b0;
          predicted_digit_reg <= 4'd0;
          if (start_btn_edge) begin
            calc_counter <= 8'd0;
            tstate <= T_CALC;
          end
        end

        T_CALC: begin
          // Simulate calculation for 50 clock cycles
          if (calc_counter < 8'd50) begin
            calc_counter <= calc_counter + 1'b1;
          end else begin
            predicted_digit_reg <= 4'd7; // Simulate result
            tstate <= T_DONE;
          end
        end

        T_DONE: begin
          done_reg <= 1'b1;
          // Stay in DONE state - predicted_digit remains displayed
        end

        default: tstate <= T_IDLE;
      endcase
    end
  end

  // Test sequence
  initial begin
    $dumpfile("start_reset_test.vcd");
    $dumpvars(0, tb_start_reset);

    // Initialize
    rst_n = 0;
    start_btn = 0;
    
    // Wait a few cycles
    #20;
    
    // Release reset
    rst_n = 1;
    #20;
    
    $display("Time %0t: After reset - done=%b, predicted_digit=%d", $time, done, predicted_digit);
    
    // Wait in reset state
    #100;
    $display("Time %0t: Waiting - done=%b, predicted_digit=%d", $time, done, predicted_digit);
    
    // Press start button
    start_btn = 1;
    #20;
    start_btn = 0;
    #20;
    
    $display("Time %0t: Start pressed - done=%b, predicted_digit=%d", $time, done, predicted_digit);
    
    // Wait for calculation to complete
    #600;
    $display("Time %0t: After calculation - done=%b, predicted_digit=%d", $time, done, predicted_digit);
    
    // Test reset while in DONE state
    #100;
    rst_n = 0;
    #20;
    $display("Time %0t: Reset pressed - done=%b, predicted_digit=%d", $time, done, predicted_digit);
    
    rst_n = 1;
    #20;
    $display("Time %0t: Reset released - done=%b, predicted_digit=%d", $time, done, predicted_digit);
    
    // Verify it stays in reset state until start is pressed again
    #100;
    $display("Time %0t: Still waiting - done=%b, predicted_digit=%d", $time, done, predicted_digit);
    
    // Press start again
    start_btn = 1;
    #20;
    start_btn = 0;
    #20;
    
    // Wait for second calculation
    #600;
    $display("Time %0t: Second calculation done - done=%b, predicted_digit=%d", $time, done, predicted_digit);
    
    $display("Test completed successfully!");
    $finish;
  end

endmodule

mnist_fpga/start_reset_test.vcd
$date
	Tue Sep  9 15:53:37 2025
$end
$version
	Icarus Verilog
$end
$timescale
	1ps
$end
$scope module tb_start_reset $end
$var wire 1 ! done $end
$var wire 4 " predicted_digit [3:0] $end
$var wire 1 # rst $end
$var wire 1 $ start_btn_edge $end
$var parameter 3 % T_CALC $end
$var parameter 3 & T_DONE $end
$var parameter 3 ' T_IDLE $end
$var parameter 3 ( T_WAIT $end
$var reg 8 ) calc_counter [7:0] $end
$var reg 1 * clk $end
$var reg 1 + done_reg $end
$var reg 4 , predicted_digit_reg [3:0] $end
$var reg 1 - rst_n $end
$var reg 1 . start_btn $end
$var reg 1 / start_btn_prev $end
$var reg 1 0 start_btn_sync1 $end
$var reg 1 1 start_btn_sync2 $end
$var reg 3 2 tstate [2:0] $end
$upscope $end
$enddefinitions $end
$comment Show the parameter values. $end
$dumpall
b1 (
b0 '
b11 &
b10 %
$end
#0
$dumpvars
bx 2
x1
x0
x/
0.
0-
bx ,
x+
0*
bx )
x$
1#
bx "
x!
$end
#5000
0$
0/
01
00
b0 )
b0 "
b0 ,
0!
0+
b0 2
1*
#10000
0*
#15000
1*
#20000
0#
0*
1-
#25000
b1 2
1*
#30000
0*
#35000
1*
#40000
0*
#45000
1*
#50000
0*
#55000
1*
#60000
0*
#65000
1*
#70000
0*
#75000
1*
#80000
0*
#85000
1*
#90000
0*
#95000
1*
#100000
0*
#105000
1*
#110000
0*
#115000
1*
#120000
0*
#125000
1*
#130000
0*
#135000
1*
#140000
0*
1.
#145000
10
1*
#150000
0*
#155000
1$
11
1*
#160000
0*
0.
#165000
0$
1/
00
b10 2
1*
#170000
0*
#175000
b1 )
01
1*
#180000
0*
#185000
0/
b10 )
1*
#190000
0*
#195000
b11 )
1*
#200000
0*
#205000
b100 )
1*
#210000
0*
#215000
b101 )
1*
#220000
0*
#225000
b110 )
1*
#230000
0*
#235000
b111 )
1*
#240000
0*
#245000
b1000 )
1*
#250000
0*
#255000
b1001 )
1*
#260000
0*
#265000
b1010 )
1*
#270000
0*
#275000
b1011 )
1*
#280000
0*
#285000
b1100 )
1*
#290000
0*
#295000
b1101 )
1*
#300000
0*
#305000
b1110 )
1*
#310000
0*
#315000
b1111 )
1*
#320000
0*
#325000
b10000 )
1*
#330000
0*
#335000
b10001 )
1*
#340000
0*
#345000
b10010 )
1*
#350000
0*
#355000
b10011 )
1*
#360000
0*
#365000
b10100 )
1*
#370000
0*
#375000
b10101 )
1*
#380000
0*
#385000
b10110 )
1*
#390000
0*
#395000
b10111 )
1*
#400000
0*
#405000
b11000 )
1*
#410000
0*
#415000
b11001 )
1*
#420000
0*
#425000
b11010 )
1*
#430000
0*
#435000
b11011 )
1*
#440000
0*
#445000
b11100 )
1*
#450000
0*
#455000
b11101 )
1*
#460000
0*
#465000
b11110 )
1*
#470000
0*
#475000
b11111 )
1*
#480000
0*
#485000
b100000 )
1*
#490000
0*
#495000
b100001 )
1*
#500000
0*
#505000
b100010 )
1*
#510000
0*
#515000
b100011 )
1*
#520000
0*
#525000
b100100 )
1*
#530000
0*
#535000
b100101 )
1*
#540000
0*
#545000
b100110 )
1*
#550000
0*
#555000
b100111 )
1*
#560000
0*
#565000
b101000 )
1*
#570000
0*
#575000
b101001 )
1*
#580000
0*
#585000
b101010 )
1*
#590000
0*
#595000
b101011 )
1*
#600000
0*
#605000
b101100 )
1*
#610000
0*
#615000
b101101 )
1*
#620000
0*
#625000
b101110 )
1*
#630000
0*
#635000
b101111 )
1*
#640000
0*
#645000
b110000 )
1*
#650000
0*
#655000
b110001 )
1*
#660000
0*
#665000
b110010 )
1*
#670000
0*
#675000
b11 2
b111 "
b111 ,
1*
#680000
0*
#685000
1!
1+
1*
#690000
0*
#695000
1*
#700000
0*
#705000
1*
#710000
0*
#715000
1*
#720000
0*
#725000
1*
#730000
0*
#735000
1*
#740000
0*
#745000
1*
#750000
0*
#755000
1*
#760000
0*
#765000
1*
#770000
0*
#775000
1*
#780000
0*
#785000
1*
#790000
0*
#795000
1*
#800000
0*
#805000
1*
#810000
0*
#815000
1*
#820000
0*
#825000
1*
#830000
0*
#835000
1*
#840000
0*
#845000
1*
#850000
0*
#855000
1*
#860000
0*
#865000
1*
#870000
0*
#875000
1*
#880000
1#
0*
0-
#885000
b0 )
b0 "
b0 ,
0!
0+
b0 2
1*
#890000
0*
#895000
1*
#900000
0#
0*
1-
#905000
b1 2
1*
#910000
0*
#915000
1*
#920000
0*
#925000
1*
#930000
0*
#935000
1*
#940000
0*
#945000
1*
#950000
0*
#955000
1*
#960000
0*
#965000
1*
#970000
0*
#975000
1*
#980000
0*
#985000
1*
#990000
0*
#995000
1*
#1000000
0*
#1005000
1*
#1010000
0*
#1015000
1*
#1020000
0*
1.
#1025000
10
1*
#1030000
0*
#1035000
1$
11
1*
#1040000
0*
0.
#1045000
0$
1/
00
b10 2
1*
#1050000
0*
#1055000
b1 )
01
1*
#1060000
0*
#1065000
0/
b10 )
1*
#1070000
0*
#1075000
b11 )
1*
#1080000
0*
#1085000
b100 )
1*
#1090000
0*
#1095000
b101 )
1*
#1100000
0*
#1105000
b110 )
1*
#1110000
0*
#1115000
b111 )
1*
#1120000
0*
#1125000
b1000 )
1*
#1130000
0*
#1135000
b1001 )
1*
#1140000
0*
#1145000
b1010 )
1*
#1150000
0*
#1155000
b1011 )
1*
#1160000
0*
#1165000
b1100 )
1*
#1170000
0*
#1175000
b1101 )
1*
#1180000
0*
#1185000
b1110 )
1*
#1190000
0*
#1195000
b1111 )
1*
#1200000
0*
#1205000
b10000 )
1*
#1210000
0*
#1215000
b10001 )
1*
#1220000
0*
#1225000
b10010 )
1*
#1230000
0*
#1235000
b10011 )
1*
#1240000
0*
#1245000
b10100 )
1*
#1250000
0*
#1255000
b10101 )
1*
#1260000
0*
#1265000
b10110 )
1*
#1270000
0*
#1275000
b10111 )
1*
#1280000
0*
#1285000
b11000 )
1*
#1290000
0*
#1295000
b11001 )
1*
#1300000
0*
#1305000
b11010 )
1*
#1310000
0*
#1315000
b11011 )
1*
#1320000
0*
#1325000
b11100 )
1*
#1330000
0*
#1335000
b11101 )
1*
#1340000
0*
#1345000
b11110 )
1*
#1350000
0*
#1355000
b11111 )
1*
#1360000
0*
#1365000
b100000 )
1*
#1370000
0*
#1375000
b100001 )
1*
#1380000
0*
#1385000
b100010 )
1*
#1390000
0*
#1395000
b100011 )
1*
#1400000
0*
#1405000
b100100 )
1*
#1410000
0*
#1415000
b100101 )
1*
#1420000
0*
#1425000
b100110 )
1*
#1430000
0*
#1435000
b100111 )
1*
#1440000
0*
#1445000
b101000 )
1*
#1450000
0*
#1455000
b101001 )
1*
#1460000
0*
#1465000
b101010 )
1*
#1470000
0*
#1475000
b101011 )
1*
#1480000
0*
#1485000
b101100 )
1*
#1490000
0*
#1495000
b101101 )
1*
#1500000
0*
#1505000
b101110 )
1*
#1510000
0*
#1515000
b101111 )
1*
#1520000
0*
#1525000
b110000 )
1*
#1530000
0*
#1535000
b110001 )
1*
#1540000
0*
#1545000
b110010 )
1*
#1550000
0*
#1555000
b11 2
b111 "
b111 ,
1*
#1560000
0*
#1565000
1!
1+
1*
